Workbook

Sheet Financial Statement (Ex-12)
B2: Tiffany & Co. Financial Statements
B4: Income Statement Data | C4: 2014 | D4: 2015 | E4: 2016 | F4: 2017 | G4: 2018
B5: Revenues | C5: 4250 | D5: 4105 | E5: 4002 | F5: 4170 | G5: 4442
B6: Gross profit | C6: 2544 | D6: 2505 | E6: 2499 | F6: 2611 | G6: 2811
B7: Selling, general, and administrative (SG&A) expenses | C7: 1633 | D7: 1706 | E7: 1753 | F7: 1801 | G7: 2021
B8: Earnings from operations | C8: 912 | D8: 799 | E8: 746 | F8: 809 | G8: 790
B9: Net earnings | C9: 484 | D9: 464 | E9: 446 | F9: 370 | G9: 586
B10: Per share of common stock (diluted) | C10: 3.73 | D10: 3.59 | E10: 3.55 | F10: 2.96 | G10: 4.75
B11: Dividends paid per share | C11: 2.15 | D11: 1.95 | E11: 1.75 | F11: 1.58 | G11: 1.48
B12: Balance Sheet Data | C12: 2014 | D12: 2015 | E12: 2016 | F12: 2017 | G12: 2018
B13: Cash and cash equivalents | C13: 730 | D13: 844 | E13: 928 | F13: 971 | G13: 793
B14: Inventories, net | C14: 2362 | D14: 2225 | E14: 2158 | F14: 2254 | G14: 2428
B15: Working capital | C15: 2851 | D15: 2779 | E15: 2941 | F15: 3259 | G15: 3041
... B31: Number of employees | C31: 12000 | D31: 12200 | E31: 11900 | F31: 13100 | G31: 14200

Sheet Comparable Comps
C2: Revenue | D2: EBITDA | E2: EBIT | F2: Net Income | H2: Current | I2: Current
H3: Assets | I3: Liabilities
B4: Burberry Group plc | C4: 3548 | D4: 925 | E4: 605 | F4: 456 | H4: 1544 | I4: 912
B5: Capri Holdings Limited | C5: 5571 | D5: 640 | E5: 441 | F5: 337 | H5: 1895 | I5: 1803
B6: Kering SA | C6: 16772 | D6: 5997 | E6: 4612 | F6: 2284 | H6: 7190 | I6: 8581
B7: Pandora A/S | C7: 3294 | D7: 1061 | E7: 628 | F7: 468 | H7: 6268 | I7: 10159
B8: Prada S.p.A. | C8: 3624 | D8: 998 | E8: 352 | F8: 290 | H8: 13860 | I8: 10642
B9: Ralph Lauren Corporation | C9: 6367 | D9: 1080 | E9: 647 | F9: 451 | H9: 3387 | I9: 1736
B10: Tapestry, Inc. | C10: 6004 | D10: 1052 | E10: 695 | F10: 541 | H10: 2204 | I10: 1212
B11: LVMH Moét Hennessy Louis Vuitton | C11: 56568 | D11: 16304 | E11: 11563 | F11: 7464 | H11: 24106 | I11: 21048
B12: Tiffany & co. | C12: 4385 | D12: 967 | E12: 738 | F12: 561 | H12: 3674 | I12: 871
C15: Share Price | D15: Shares Out | E15: Debt | F15: Bond Rating | G15: Beta | H15: Employees | I15: Dividend
I16: Yield
B17: Burberry Group plc | C17: 24.59 | D17: 413 | E17: 873 | F17: A—* | G17: 1.15 | H17: 10629 | I17: 0.022
B18: Capri Holdings Limited | C18: 30.97 | D18: 152 | E18: 3562 | F18: BBB- | G18: 0.97 | H18: 17797 | I18: 0
B19: Kering SA | C19: 530.96 | D19: 126 | E19: 6170 | F19: A— | G19: 1.09 | H19: 34795 | I19: 0.026
B20: Pandora A/S | C20: 40.43 | D20: 92 | E20: 6963 | F20: BBB * | G20: 1.52 | H20: 32000 | I20: 0.068
B21: Prada S.p.A. | C21: 3.1 | D21: 2559 | E21: 23149 | F21: BB* | G21: 1.68 | H21: 13556 | I21: 0.02
B22: Ralph Lauren Corporation | C22: 95.08 | D22: 79 | E22: 2244 | F22: A— | G22: 1.05 | H22: 24300 | I22: 0.019
B23: Tapestry, Inc. | C23: 25.44 | D23: 286 | E23: 3568 | F23: BBB- | G23: 1.08 | H23: 21000 | I23: 0.043
B24: LVMH Moet Hennessy Louis Vuitton | C24: 416.57 | D24: 505 | E24: 15727 | F24: A+ | G24: 1.14 | H24: 127739 | I24: 0.023
B25: Tiffany & co. | C25: 91.58 | D25: 122 | E25: 1854 | F25: BBB+ | G25: 1.05 | H25: 14200 | I25: 0.024

Sheet Financial Forecast (Ex-13)
C2: 2018 | D2: 2019 | E2: 2020F | F2: 2021F | G2: 2022F | H2: 2023F | I2: 2024F | J2: 2025F | K2: 2026F | L2: 2027F
B3: Revenue growth by region
B4: Americas | D4: -0.011 | E4: 0.04 | F4: 0.04 | G4: 0.04 | H4: 0.04 | I4: 0.03 | J4: 0.03 | K4: 0.03 | L4: 0.03
B5: Asia Pacific | D5: 0.006 | E5: 0.07 | F5: 0.07 | G5: 0.07 | H5: 0.07 | I5: 0.03 | J5: 0.03 | K5: 0.03 | L5: 0.03
B6: Europe | D6: -0.039 | E6: 0.03 | F6: 0.03 | G6: 0.03 | H6: 0.03 | I6: 0.03 | J6: 0.03 | K6: 0.03 | L6: 0.03
B7: Other | D7: -0.073 | E7: 0.02 | F7: 0.02 | G7: 0.02 | H7: 0.02 | I7: 0.03 | J7: 0.03 | K7: 0.03 | L7: 0.03
B9: Gross margin by region
B10: Americas | D10: 0.62 | E10: 0.62 | F10: 0.62 | G10: 0.62 | H10: 0.62 | I10: 0.6 | J10: 0.6 | K10: 0.6 | L10: 0.6
B11: Asia Pacific | D11: 0.653 | E11: 0.66 | F11: 0.66 | G11: 0.66 | H11: 0.66 | I11: 0.63 | J11: 0.63 | K11: 0.63 | L11: 0.63
B12: Europe | D12: 0.596 | E12: 0.6 | F12: 60.00/0 | G12: 0.6 | H12: 0.6 | I12: 0.61 | J12: 0.61 | K12: 0.61 | L12: 0.61
B13: Other | D13: 0.577 | E13: 0.58 | F13: 0.58 | G13: 0.58 | H13: 0.58 | I13: 0.6 | J13: 0.6 | K13: 0.6 | L13: 0.6
B15: SG&A as a percentage of revenue | D15: 0.456 | E15: 0.45 | F15: 0.45 | G15: 0.45 | H15: 0.45 | I15: 0.45 | J15: 0.45 | K15: 0.45 | L15: 0.45
B17: Revenues by region | N17: Total Forecasted Sales - Region Wise
B18: Americas | C18: 1960 | D18: 1938 | E18: 2016 | F18: 2096 | G18: 2180 | H18: 2267 | I18: 2335 | J18: 2406 | K18: 2478 | L18: 2552 | N18: =SUM(E18:L18) -> 18330 | O18: =N18/$N$23 -> 0.42385423
B19: Asia Pacific | C19: 1882 | D19: 1894 | E19: 2027 | F19: 2168 | G19: 2320 | H19: 2483 | I19: 2557 | J19: 2634 | K19: 2713 | L19: 2794 | N19: =SUM(E19:L19) -> 19696 | O19: =N19/$N$23 -> 0.45544097
B20: Europe | C20: 504 | D20: 485 | E20: 499 | F20: 514 | G20: 529 | H20: 545 | I20: 562 | J20: 579 | K20: 596 | L20: 614 | N20: =SUM(E20:L20) -> 4438 | O20: =N20/$N$23 -> 0.10262221
B21: Other | C21: 95 | D21: 88 | E21: 90 | F21: 92 | G21: 93 | H21: 95 | I21: 98 | J21: 101 | K21: 104 | L21: 107 | N21: =SUM(E21:L21) -> 780 | O21: =N21/$N$23 -> 0.01803635
B23: Revenues | C23: 4442 | D23: 4405 | E23: 4631 | F23: 4871 | G23: 5123 | H23: 5391 | I23: 5553 | J23: 5719 | K23: 5891 | L23: 6067 | N23: =SUM(E23:L23) -> 43246
B24: Growth | D24: -0.01 | E24: 0.05 | F24: 0.05 | G24: 0.05 | H24: 0.04 | I24: 0.04 | J24: 0.04 | K24: 0.04 | L24: 0.03
B26: Gross profit bv region
B27: Americas | D27: 1202 | E27: 1250 | F27: 1300 | G27: 1352 | H27: 1406 | I27: 1401 | J27: 1443 | K27: 1486 | L27: 1531
B28: Asia Pacific | D28: 1236 | E28: 1338 | F28: 1431 | G28: 1531 | H28: 1639 | I28: 1611 | J28: 1659 | K28: 1709 | L28: 1760
B29: Europe | D29: 289 | E29: 299 | F29: 308 | G29: 318 | H29: 327 | I29: 343 | J29: 353 | K29: 364 | L29: 374
B30: Other | D30: 51 | E30: 52 | F30: 53 | G30: 54 | H30: 55 | I30: 59 | J30: 61 | K30: 63 | L30: 64
B32: Gross profit | C32: 2811 | D32: 2777 | E32: 2939 | F32: 3092 | G32: 3255 | H32: 3427 | I32: 3414 | J32: 3516 | K32: 3622 | L32: 3730
B34: SC,&A | C34: 2021 | D34: 2009 | E34: 2084 | F34: 2192 | G34: 2306 | H34: 2426 | I34: 2499 | J34: 2574 | K34: 2651 | L34: 2730
B35: Operating profit | C35: 790 | D35: 769 | E35: 855 | F35: 901 | G35: 949 | H35: 1001 | I35: 915 | J35: 943 | K35: 971 | L35: 1000
B38: Working capital | C38: 3041 | D38: 3016 | E38: 3171 | F38: 3335 | G38: 3508 | H38: 3691 | I38: 3802 | J38: 3916 | K38: 4033 | L38: 4154
B39: Net property, plant, & equipment | C39: 991 | D39: 982 | E39: 1033 | F39: 1086 | G39: 1142 | H39: 1202 | I39: 1238 | J39: 1275 | K39: 1314 | L39: 1353
B40: Depreciation & amortization | C40: 229 | D40: 227 | E40: 239 | F40: 251 | G40: 264 | H40: 278 | I40: 286 | J40: 295 | K40: 304 | L40: 313
B41: Working capital turnover | C41: 1.46 | D41: 1.46 | E41: 1.46 | F41: 1.46 | G41: 1.46 | H41: 1.46 | I41: 1.46 | J41: 1.46 | K41: 1.46 | L41: 1.46
B42: PP &E turnover | C42: 4.48 | D42: 4.48 | E42: 4.48 | F42: 4.48 | G42: 4.48 | H42: 4.48 | I42: 4.48 | J42: 4.48 | K42: 4.48 | L42: 4.48
B44: Change in NWC | D44: =D38-C38 -> -25 | E44: =E38-D38 -> 155 | F44: =F38-E38 -> 164 | G44: =G38-F38 -> 173 | H44: =H38-G38 -> 183 | I44: =I38-H38 -> 111 | J44: =J38-I38 -> 114 | K44: =K38-J38 -> 117 | L44: =L38-K38 -> 121
B45: CapEx | D45: =C39-D39+D40 -> 236 | E45: =D39-E39+E40 -> 188 | F45: =E39-F39+F40 -> 198 | G45: =F39-G39+G40 -> 208 | H45: =G39-H39+H40 -> 218 | I45: =H39-I39+I40 -> 250 | J45: =I39-J39+J40 -> 258 | K45: =J39-K39+K40 -> 265 | L45: =K39-L39+L40 -> 274
B46: CapEx (as a % of Revenue) | D46: =D45/D23 -> 0.053575482 | E46: =E45/E23 -> 0.040595984 | F46: =F45/F23 -> 0.040648737 | G46: =G45/G23 -> 0.04060121 | H46: =H45/H23 -> 0.040437767 | I46: =I45/I23 -> 0.04502071 | J46: =J45/J23 -> 0.045112782 | K46: =K45/K23 -> 0.044983874 | L46: =L45/L23 -> 0.045162354
B48: CapEx (6% of Revenue) - Based on Historical Average | D48: =D23*6% -> 264.3 | E48: =E23*6% -> 277.86 | F48: =F23*6% -> 292.26 | G48: =G23*6% -> 307.38 | H48: =H23*6% -> 323.46 | I48: =I23*6% -> 333.18 | J48: =J23*6% -> 343.14 | K48: =K23*6% -> 353.46 | L48: =L23*6% -> 364.02

Sheet WACC
B2: Weighted Average Cost of Capital Analysis
H5: Debt to | I5: Debt to | J5: Levered | K5: Unlevered
B6: Company | C6: Share Price | D6: Shares O/s | E6: Market Cap | F6: Debt | G6: Total Capital | H6: Equity | I6: Capital | J6: Beta | K6: Beta
B7: Burberry Group plc | C7: ='Comparable Comps'!C17 -> 24.59 | D7: ='Comparable Comps'!D17 -> 413 | E7: =C7*D7 -> 10155.67 | F7: ='Comparable Comps'!E17 -> 873 | G7: =E7+F7 -> 11028.67 | H7: =F7/E7 -> 0.085961832 | I7: =F7/G7 -> 0.079157324 | J7: ='Comparable Comps'!G17 -> 1.15 | K7: =J7/(1+(1-21%)*H7) -> 1.0768699
B8: Capri Holdings Limited | C8: ='Comparable Comps'!C18 -> 30.97 | D8: ='Comparable Comps'!D18 -> 152 | E8: =C8*D8 -> 4707.44 | F8: ='Comparable Comps'!E18 -> 3562 | G8: =E8+F8 -> 8269.44 | H8: =F8/E8 -> 0.75667454 | I8: =F8/G8 -> 0.43074259 | J8: ='Comparable Comps'!G18 -> 0.97 | K8: =J8/(1+(1-21%)*H8) -> 0.60709504
B9: Kering SA | C9: ='Comparable Comps'!C19 -> 530.96 | D9: ='Comparable Comps'!D19 -> 126 | E9: =C9*D9 -> 66900.96 | F9: ='Comparable Comps'!E19 -> 6170 | G9: =E9+F9 -> 73070.96 | H9: =F9/E9 -> 0.092225881 | I9: =F9/G9 -> 0.084438469 | J9: ='Comparable Comps'!G19 -> 1.09 | K9: =J9/(1+(1-21%)*H9) -> 1.0159775
B10: Pandora A/S | C10: ='Comparable Comps'!C20 -> 40.43 | D10: ='Comparable Comps'!D20 -> 92 | E10: =C10*D10 -> 3719.56 | F10: ='Comparable Comps'!E20 -> 6963 | G10: =E10+F10 -> 10682.56 | H10: =F10/E10 -> 1.8719956 | I10: =F10/G10 -> 0.65181005 | J10: ='Comparable Comps'!G20 -> 1.52 | K10: =J10/(1+(1-21%)*H10) -> 0.613181
B11: Prada S.p.A. | C11: ='Comparable Comps'!C21 -> 3.1 | D11: ='Comparable Comps'!D21 -> 2559 | E11: =C11*D11 -> 7932.9 | F11: ='Comparable Comps'!E21 -> 23149 | G11: =E11+F11 -> 31081.9 | H11: =F11/E11 -> 2.9181006 | I11: =F11/G11 -> 0.74477429 | J11: ='Comparable Comps'!G21 -> 1.68 | K11: =J11/(1+(1-21%)*H11) -> 0.50827467
B12: Ralph Lauren Corporation | C12: ='Comparable Comps'!C22 -> 95.08 | D12: ='Comparable Comps'!D22 -> 79 | E12: =C12*D12 -> 7511.32 | F12: ='Comparable Comps'!E22 -> 2244 | G12: =E12+F12 -> 9755.32 | H12: =F12/E12 -> 0.29874909 | I12: =F12/G12 -> 0.23002833 | J12: ='Comparable Comps'!G22 -> 1.05 | K12: =J12/(1+(1-21%)*H12) -> 0.84950647
B13: Tapestry, Inc. | C13: ='Comparable Comps'!C23 -> 25.44 | D13: ='Comparable Comps'!D23 -> 286 | E13: =C13*D13 -> 7275.84 | F13: ='Comparable Comps'!E23 -> 3568 | G13: =E13+F13 -> 10843.84 | H13: =F13/E13 -> 0.49039011 | I13: =F13/G13 -> 0.32903473 | J13: ='Comparable Comps'!G23 -> 1.08 | K13: =J13/(1+(1-21%)*H13) -> 0.77842989
B14: LVMH Moet Hennessy Louis Vuitton | C14: ='Comparable Comps'!C24 -> 416.57 | D14: ='Comparable Comps'!D24 -> 505 | E14: =C14*D14 -> 210367.85 | F14: ='Comparable Comps'!E24 -> 15727 | G14: =E14+F14 -> 226094.85 | H14: =F14/E14 -> 0.074759522 | I14: =F14/G14 -> 0.069559302 | J14: ='Comparable Comps'!G24 -> 1.14 | K14: =J14/(1+(1-21%)*H14) -> 1.0764262
B15: Tiffany & co. | C15: ='Comparable Comps'!C25 -> 91.58 | D15: ='Comparable Comps'!D25 -> 122 | E15: =C15*D15 -> 11172.76 | F15: ='Comparable Comps'!E25 -> 1854 | G15: =E15+F15 -> 13026.76 | H15: =F15/E15 -> 0.1659393 | I15: =F15/G15 -> 0.14232242 | J15: ='Comparable Comps'!G25 -> 1.05 | K15: =J15/(1+(1-21%)*H15) -> 0.92830641
G17: Mean | H17: =AVERAGE(H7:H15) -> 0.75053294 | I17: =AVERAGE(I7:I15) -> 0.30687417 | J17: =AVERAGE(J7:J15) -> 1.1922222 | K17: =AVERAGE(K7:K15) -> 0.82822968
G18: Median | H18: =MEDIAN(H7:H15) -> 0.29874909 | I18: =MEDIAN(I7:I15) -> 0.23002833 | J18: =MEDIAN(J7:J15) -> 1.09 | K18: =MEDIAN(K7:K15) -> 0.84950647
B21: Cost of Debt | H21: Cost of Equity
B22: Credit Rating (estimated) | C22: BBB+ | H22: Risk Free Rate | K22: 0.0211
B23: Bond Yield as per Credit Rating | C23: 0.0348 | H23: Relevered Beta | K23: =K33 -> 1.05
B24: Marginal tax Rate | C24: 0.21 | H24: Market Risk Premium | K24: 0.06
B25: After Tax Cost of Debt | C25: =C23*(1-C24) -> 0.027492 | H25: Cost of Equity | K25: =K22+K23*K24 -> 0.0841
B28: Capital Structure | D28: Current | E28: Target | H28: Relevered Beta
B29: Debt | C29: =F15 -> 1854 | D29: =C29/$C$31 -> 0.14232242 | E29: =I18 -> 0.23002833 | H29: Unlevered Beta (Median) | K29: =K18 -> 0.84950647
B30: Market Capitalization | C30: =E15 -> 11172.76 | D30: =C30/$C$31 -> 0.85767758 | E30: =E31-E29 -> 0.76997167 | H30: Target D/E Ratio | K30: =E33 -> 0.29874909
B31: Total Capital | C31: =SUM(C29:C30) -> 13026.76 | D31: =SUM(D29:D30) -> 1 | E31: =D31 -> 1 | H31: Tax rate | K31: =C24 -> 0.21
B33: Debt to Equity Ratio | D33: =D29/D30 -> 0.1659393 | E33: =E29/E30 -> 0.29874909 | H33: Relevered Beta | K33: =K29*(1+(1-K31)*K30) -> 1.05
B36: Weighted Average Cost of Capital (WACC)
B38: Cost of Equity | E38: =K25 -> 0.0841
B39: Weight of Equity | E39: =E30 -> 0.76997167
B41: Cost of Debt | E41: =C25 -> 0.027492
B42: Weight of Debt | E42: =E29 -> 0.23002833
B44: WACC | E44: =E38*E39+E41*E42 -> 0.071078556

Sheet DCF
B2: Discounted Cash Flow Analysis - Tiffany & Co.
C4: ='Financial Forecast (Ex-13)'!D2 -> 2019 | D4: ='Financial Forecast (Ex-13)'!E2 -> 2020F | E4: ='Financial Forecast (Ex-13)'!F2 -> 2021F | F4: ='Financial Forecast (Ex-13)'!G2 -> 2022F | G4: ='Financial Forecast (Ex-13)'!H2 -> 2023F | H4: ='Financial Forecast (Ex-13)'!I2 -> 2024F | I4: ='Financial Forecast (Ex-13)'!J2 -> 2025F | J4: ='Financial Forecast (Ex-13)'!K2 -> 2026F | K4: ='Financial Forecast (Ex-13)'!L2 -> 2027F | L4: Terminal Period
B5: Operating Income | C5: ='Financial Forecast (Ex-13)'!D35 -> 769 | D5: ='Financial Forecast (Ex-13)'!E35 -> 855 | E5: ='Financial Forecast (Ex-13)'!F35 -> 901 | F5: ='Financial Forecast (Ex-13)'!G35 -> 949 | G5: ='Financial Forecast (Ex-13)'!H35 -> 1001 | H5: ='Financial Forecast (Ex-13)'!I35 -> 915 | I5: ='Financial Forecast (Ex-13)'!J35 -> 943 | J5: ='Financial Forecast (Ex-13)'!K35 -> 971 | K5: ='Financial Forecast (Ex-13)'!L35 -> 1000
B6: Tax Rate | C6: 0.21 | D6: =C6 -> 0.21 | E6: =D6 -> 0.21 | F6: =E6 -> 0.21 | G6: =F6 -> 0.21 | H6: =G6 -> 0.21 | I6: =H6 -> 0.21 | J6: =I6 -> 0.21 | K6: =J6 -> 0.21
B7: NOPAT | C7: =C5*(1-C6) -> 607.51 | D7: =D5*(1-D6) -> 675.45 | E7: =E5*(1-E6) -> 711.79 | F7: =F5*(1-F6) -> 749.71 | G7: =G5*(1-G6) -> 790.79 | H7: =H5*(1-H6) -> 722.85 | I7: =I5*(1-I6) -> 744.97 | J7: =J5*(1-J6) -> 767.09 | K7: =K5*(1-K6) -> 790
B8: (+) D&A | C8: ='Financial Forecast (Ex-13)'!D40 -> 227 | D8: ='Financial Forecast (Ex-13)'!E40 -> 239 | E8: ='Financial Forecast (Ex-13)'!F40 -> 251 | F8: ='Financial Forecast (Ex-13)'!G40 -> 264 | G8: ='Financial Forecast (Ex-13)'!H40 -> 278 | H8: ='Financial Forecast (Ex-13)'!I40 -> 286 | I8: ='Financial Forecast (Ex-13)'!J40 -> 295 | J8: ='Financial Forecast (Ex-13)'!K40 -> 304 | K8: ='Financial Forecast (Ex-13)'!L40 -> 313
B9: (-) CapEx | C9: ='Financial Forecast (Ex-13)'!D45 -> 236 | D9: ='Financial Forecast (Ex-13)'!E45 -> 188 | E9: ='Financial Forecast (Ex-13)'!F45 -> 198 | F9: ='Financial Forecast (Ex-13)'!G45 -> 208 | G9: ='Financial Forecast (Ex-13)'!H45 -> 218 | H9: ='Financial Forecast (Ex-13)'!I45 -> 250 | I9: ='Financial Forecast (Ex-13)'!J45 -> 258 | J9: ='Financial Forecast (Ex-13)'!K45 -> 265 | K9: ='Financial Forecast (Ex-13)'!L45 -> 274
B10: (-) Change in NWC | C10: ='Financial Forecast (Ex-13)'!D44 -> -25 | D10: ='Financial Forecast (Ex-13)'!E44 -> 155 | E10: ='Financial Forecast (Ex-13)'!F44 -> 164 | F10: ='Financial Forecast (Ex-13)'!G44 -> 173 | G10: ='Financial Forecast (Ex-13)'!H44 -> 183 | H10: ='Financial Forecast (Ex-13)'!I44 -> 111 | I10: ='Financial Forecast (Ex-13)'!J44 -> 114 | J10: ='Financial Forecast (Ex-13)'!K44 -> 117 | K10: ='Financial Forecast (Ex-13)'!L44 -> 121
B12: Free Cash Flow | C12: =C7+C8-C9-C10 -> 623.51 | D12: =D7+D8-D9-D10 -> 571.45 | E12: =E7+E8-E9-E10 -> 600.79 | F12: =F7+F8-F9-F10 -> 632.71 | G12: =G7+G8-G9-G10 -> 667.79 | H12: =H7+H8-H9-H10 -> 647.85 | I12: =I7+I8-I9-I10 -> 667.97 | J12: =J7+J8-J9-J10 -> 689.09 | K12: =K7+K8-K9-K10 -> 708
B14: Mid year convention | D14: 0.5 | E14: =D14+1 -> 1.5 | F14: =E14+1 -> 2.5 | G14: =F14+1 -> 3.5 | H14: =G14+1 -> 4.5 | I14: =H14+1 -> 5.5 | J14: =I14+1 -> 6.5 | K14: =J14+1 -> 7.5 | L14: =K14+0.5 -> 8
B15: Discounting Factor | D15: =1/(1+$C$20)^D14 -> 0.96624962 | E15: =1/(1+$C$20)^E14 -> 0.90212769 | F15: =1/(1+$C$20)^F14 -> 0.84226099 | G15: =1/(1+$C$20)^G14 -> 0.78636715 | H15: =1/(1+$C$20)^H14 -> 0.73418252 | I15: =1/(1+$C$20)^I14 -> 0.68546095 | J15: =1/(1+$C$20)^J14 -> 0.63997262 | K15: =1/(1+$C$20)^K14 -> 0.59750297 | L15: =1/(1+$C$20)^L14 -> 0.57733702
B17: PV of Free Cash Flows | D17: =D12*D15 -> 552.16335 | E17: =E12*E15 -> 541.98929 | F17: =F12*F15 -> 532.90695 | G17: =G12*G15 -> 525.12812 | H17: =H12*H15 -> 475.64015 | I17: =I12*I15 -> 457.86735 | J17: =J12*J15 -> 440.99873 | K17: =K12*K15 -> 423.0321
B19: Assumptions & Estimations
B20: WACC | C20: 0.071078556
B21: Terminal Growth Rate | C21: 0.025
B23: Terminal Value
B24: FCF (n+1) | C24: =K12*(1+C21) -> 725.7
B25: Terminal Value | C25: =C24/(C20-C21) -> 15749.191
B26: PV of Terminal Value | C26: =C25*L15 -> 9092.5912
B28: Enterprise Value
B29: Sum of PV of FCF | C29: =SUM(D17:K17) -> 3949.726
B30: PV of Terminal Value | C30: =C26 -> 9092.5912
B31: Enterprise Value | C31: =SUM(C29:C30) -> 13042.317
B33: Equity Value
B34: Enterprise Value | C34: =C31 -> 13042.317 | G34: WACC
B35: Debt | C35: ='Financial Statement (Ex-12)'!G17 -> 997 | F35: =C39 -> 105.23211 | G35: 0.056078556 | H35: 0.063578556 | I35: 0.071078556 | J35: 0.078578556 | K35: 0.086078556
B36: Cash | C36: ='Financial Statement (Ex-12)'!G13 -> 793 | E36: Terminal GR | F36: 0.015 | G36: 125.16961 | H36: 105.63223 | I36: 91.344468 | J36: 80.446512 | K36: 71.863686
B37: Equity Value | C37: =C34-C35+C36 -> 12838.317 | F37: 0.02 | G37: 138.53265 | H37: 114.53528 | I37: 97.608568 | J37: 85.034599 | K37: 75.329583
B38: Shares O/s | C38: ='Comparable Comps'!D25 -> 122 | F38: 0.025 | G38: 156.19547 | H38: 125.74611 | I38: 105.23211 | J38: 90.479014 | K38: 79.362929
B39: Per Share Price | C39: =C37/C38 -> 105.23211 | F39: 0.03 | G39: 180.63121 | H39: 140.29562 | I39: 114.71149 | J39: 97.044175 | K39: 84.115506
F40: 0.035 | G40: 216.65965 | H40: 159.93619 | I40: 126.81831 | J40: 105.11585 | K40: 89.798528

Sheet Comparable Comps Valuation
B2: Comparable Company Valuation - Tiffany & Co.
C5: Market Data | J5: Financial Data | O5: Valuation Multiples
B7: Company | C7: Price/share | D7: Shares O/s | E7: Market Cap | F7: Debt | G7: Cash | H7: Enterprise Value | J7: Revenue | K7: EBITDA | L7: EBIT | M7: Net Income | O7: EV/Revenue | P7: EV/EBITDA | Q7: EV/EBIT | R7: P/E
B8: ='Comparable Comps'!B4 -> Burberry Group plc | C8: ='Comparable Comps'!C17 -> 24.59 | D8: ='Comparable Comps'!D17 -> 413 | E8: =C8*D8 -> 10155.67 | F8: ='Comparable Comps'!E17 -> 873 | G8: 1250 | H8: =E8+F8-G8 -> 9778.67 | J8: ='Comparable Comps'!C4 -> 3548 | K8: ='Comparable Comps'!D4 -> 925 | L8: ='Comparable Comps'!E4 -> 605 | M8: ='Comparable Comps'!F4 -> 456 | O8: =$H8/J8 -> 2.7561077 | P8: =$H8/K8 -> 10.571535 | Q8: =$H8/L8 -> 16.163091 | R8: =$E8/M8 -> 22.271206
B9: ='Comparable Comps'!B5 -> Capri Holdings Limited | C9: ='Comparable Comps'!C18 -> 30.97 | D9: ='Comparable Comps'!D18 -> 152 | E9: =C9*D9 -> 4707.44 | F9: ='Comparable Comps'!E18 -> 3562 | G9: 163 | H9: =E9+F9-G9 -> 8106.44 | J9: ='Comparable Comps'!C5 -> 5571 | K9: ='Comparable Comps'!D5 -> 640 | L9: ='Comparable Comps'!E5 -> 441 | M9: ='Comparable Comps'!F5 -> 337 | O9: =$H9/J9 -> 1.455114 | P9: =$H9/K9 -> 12.666312 | Q9: =$H9/L9 -> 18.38195 | R9: =$E9/M9 -> 13.968665
B10: ='Comparable Comps'!B6 -> Kering SA | C10: ='Comparable Comps'!C19 -> 530.96 | D10: ='Comparable Comps'!D19 -> 126 | E10: =C10*D10 -> 66900.96 | F10: ='Comparable Comps'!E19 -> 6170 | G10: 5310 | H10: =E10+F10-G10 -> 67760.96 | J10: ='Comparable Comps'!C6 -> 16772 | K10: ='Comparable Comps'!D6 -> 5997 | L10: ='Comparable Comps'!E6 -> 4612 | M10: ='Comparable Comps'!F6 -> 2284 | O10: =$H10/J10 -> 4.040124 | P10: =$H10/K10 -> 11.299143 | Q10: =$H10/L10 -> 14.692316 | R10: =$E10/M10 -> 29.291138
B11: ='Comparable Comps'!B7 -> Pandora A/S | C11: ='Comparable Comps'!C20 -> 40.43 | D11: ='Comparable Comps'!D20 -> 92 | E11: =C11*D11 -> 3719.56 | F11: ='Comparable Comps'!E20 -> 6963 | G11: 215 | H11: =E11+F11-G11 -> 10467.56 | J11: ='Comparable Comps'!C7 -> 3294 | K11: ='Comparable Comps'!D7 -> 1061 | L11: ='Comparable Comps'!E7 -> 628 | M11: ='Comparable Comps'!F7 -> 468 | O11: =$H11/J11 -> 3.1777656 | P11: =$H11/K11 -> 9.8657493 | Q11: =$H11/L11 -> 16.668089 | R11: =$E11/M11 -> 7.9477778
B12: ='Comparable Comps'!B8 -> Prada S.p.A. | C12: ='Comparable Comps'!C21 -> 3.1 | D12: ='Comparable Comps'!D21 -> 2559 | E12: =C12*D12 -> 7932.9 | F12: ='Comparable Comps'!E21 -> 23149 | G12: 585 | H12: =E12+F12-G12 -> 30496.9 | J12: ='Comparable Comps'!C8 -> 3624 | K12: ='Comparable Comps'!D8 -> 998 | L12: ='Comparable Comps'!E8 -> 352 | M12: ='Comparable Comps'!F8 -> 290 | O12: =$H12/J12 -> 8.4152594 | P12: =$H12/K12 -> 30.558016 | Q12: =$H12/L12 -> 86.63892 | R12: =$E12/M12 -> 27.354828
B13: ='Comparable Comps'!B9 -> Ralph Lauren Corporation | C13: ='Comparable Comps'!C22 -> 95.08 | D13: ='Comparable Comps'!D22 -> 79 | E13: =C13*D13 -> 7511.32 | F13: ='Comparable Comps'!E22 -> 2244 | G13: 2100 | H13: =E13+F13-G13 -> 7655.32 | J13: ='Comparable Comps'!C9 -> 6367 | K13: ='Comparable Comps'!D9 -> 1080 | L13: ='Comparable Comps'!E9 -> 647 | M13: ='Comparable Comps'!F9 -> 451 | O13: =$H13/J13 -> 1.2023433 | P13: =$H13/K13 -> 7.0882593 | Q13: =$H13/L13 -> 11.832025 | R13: =$E13/M13 -> 16.654812
B14: ='Comparable Comps'!B10 -> Tapestry, Inc. | C14: ='Comparable Comps'!C23 -> 25.44 | D14: ='Comparable Comps'!D23 -> 286 | E14: =C14*D14 -> 7275.84 | F14: ='Comparable Comps'!E23 -> 3568 | G14: 1250 | H14: =E14+F14-G14 -> 9593.84 | J14: ='Comparable Comps'!C10 -> 6004 | K14: ='Comparable Comps'!D10 -> 1052 | L14: ='Comparable Comps'!E10 -> 695 | M14: ='Comparable Comps'!F10 -> 541 | O14: =$H14/J14 -> 1.5979081 | P14: =$H14/K14 -> 9.1196198 | Q14: =$H14/L14 -> 13.804086 | R14: =$E14/M14 -> 13.448872
B15: ='Comparable Comps'!B11 -> LVMH Moét Hennessy Louis Vuitton | C15: ='Comparable Comps'!C24 -> 416.57 | D15: ='Comparable Comps'!D24 -> 505 | E15: =C15*D15 -> 210367.85 | F15: ='Comparable Comps'!E24 -> 15727 | G15: 6030 | H15: =E15+F15-G15 -> 220064.85 | J15: ='Comparable Comps'!C11 -> 56568 | K15: ='Comparable Comps'!D11 -> 16304 | L15: ='Comparable Comps'!E11 -> 11563 | M15: ='Comparable Comps'!F11 -> 7464 | O15: =$H15/J15 -> 3.890271 | P15: =$H15/K15 -> 13.497599 | Q15: =$H15/L15 -> 19.031813 | R15: =$E15/M15 -> 28.184331
B16: ='Comparable Comps'!B12 -> Tiffany & co. | C16: ='Comparable Comps'!C25 -> 91.58 | D16: ='Comparable Comps'!D25 -> 122 | E16: =C16*D16 -> 11172.76 | F16: ='Comparable Comps'!E25 -> 1854 | G16: ='Financial Statement (Ex-12)'!G13 -> 793 | H16: =E16+F16-G16 -> 12233.76 | J16: ='Comparable Comps'!C12 -> 4385 | K16: ='Comparable Comps'!D12 -> 967 | L16: ='Comparable Comps'!E12 -> 738 | M16: ='Comparable Comps'!F12 -> 561 | O16: =$H16/J16 -> 2.7899111 | P16: =$H16/K16 -> 12.651251 | Q16: =$H16/L16 -> 16.576911 | R16: =$E16/M16 -> 19.915793
M19: Mean | O19: =AVERAGE(O8:O16) -> 3.2583116 | P19: =AVERAGE(P8:P16) -> 13.035276 | Q19: =AVERAGE(Q8:Q16) -> 23.754356 | R19: =AVERAGE(R8:R16) -> 19.893047
M20: Median | O20: =MEDIAN(O8:O16) -> 2.7899111 | P20: =MEDIAN(P8:P16) -> 11.299143 | Q20: =MEDIAN(Q8:Q16) -> 16.576911 | R20: =MEDIAN(R8:R16) -> 19.915793
M21: Low | O21: =MIN(O8:O16) -> 1.2023433 | P21: =MIN(P8:P16) -> 7.0882593 | Q21: =MIN(Q8:Q16) -> 11.832025 | R21: =MIN(R8:R16) -> 7.9477778
M22: High | O22: =MAX(O8:O16) -> 8.4152594 | P22: =MAX(P8:P16) -> 30.558016 | Q22: =MAX(Q8:Q16) -> 86.63892 | R22: =MAX(R8:R16) -> 29.291138
B25: Tiffany & Co. | O25: EV/Revenue | P25: EV/EBITDA | Q25: EV/EBIT | R25: P/E
B26: Implied Enterprise Value | O26: =O19*J16 -> 14287.696 | P26: =P19*K16 -> 12605.112 | Q26: =Q19*L16 -> 17530.714 | R26: =R29+R27-R28 -> 12220.999
B27: Debt | O27: =F16 -> 1854 | P27: =O27 -> 1854 | Q27: =P27 -> 1854 | R27: =Q27 -> 1854
B28: Cash | O28: =G16 -> 793 | P28: =O28 -> 793 | Q28: =P28 -> 793 | R28: =Q28 -> 793
B29: Implied Equity Value | O29: =O26-O27+O28 -> 13226.696 | P29: =P26-P27+P28 -> 11544.112 | Q29: =Q26-Q27+Q28 -> 16469.714 | R29: =R19*M16 -> 11159.999
B30: Implied Price per Share | O30: =O29/$D$16 -> 108.41554 | P30: =P29/$D$16 -> 94.623869 | Q30: =Q29/$D$16 -> 134.99766 | R30: =R29/$D$16 -> 91.475405
B32: High - Valuation Analysis | O32: EV/Revenue | P32: EV/EBITDA | Q32: EV/EBIT | R32: P/E
B33: Implied Enterprise Value | O33: =O22*J16 -> 36900.912 | P33: =P22*K16 -> 29549.602 | Q33: =Q22*L16 -> 63939.523 | R33: =R36+R34-R35 -> 17493.329
B34: Debt | O34: =F16 -> 1854 | P34: =O34 -> 1854 | Q34: =P34 -> 1854 | R34: =Q34 -> 1854
B35: Cash | O35: =G16 -> 793 | P35: =O35 -> 793 | Q35: =P35 -> 793 | R35: =Q35 -> 793
B36: Implied Equity Value | O36: =O33+O35-O34 -> 35839.912 | P36: =P33+P35-P34 -> 28488.602 | Q36: =Q33+Q35-Q34 -> 62878.523 | R36: =R22*M16 -> 16432.329
B37: Implied Price per Share | O37: =O36/$D$16 -> 293.76977 | P37: =P36/$D$16 -> 233.51313 | Q37: =Q36/$D$16 -> 515.39773 | R37: =R36/$D$16 -> 134.69122
B39: Low - Valuation Analysis | O39: EV/Revenue | P39: EV/EBITDA | Q39: EV/EBIT | R39: P/E
B40: Implied Enterprise Value | O40: =O21*J16 -> 5272.2755 | P40: =P21*K16 -> 6854.3467 | Q40: =Q21*L16 -> 8732.0343 | R40: =R43+R41-R42 -> 5519.7033
B41: Debt | O41: =F16 -> 1854 | P41: =O41 -> 1854 | Q41: =P41 -> 1854 | R41: =Q41 -> 1854
B42: Cash | O42: =G16 -> 793 | P42: =O42 -> 793 | Q42: =P42 -> 793 | R42: =Q42 -> 793
B43: Implied Equity Value | O43: =O40+O42-O41 -> 4211.2755 | P43: =P40+P42-P41 -> 5793.3467 | Q43: =Q40+Q42-Q41 -> 7671.0343 | R43: =R21*M16 -> 4458.7033
B44: Implied Price per Share | O44: =O43/$D$16 -> 34.518652 | P44: =P43/$D$16 -> 47.486448 | Q44: =Q43/$D$16 -> 62.87733 | R44: =R43/$D$16 -> 36.546749

Sheet Valuation Analysis
B2: Valuation Analysis - Tiffany & Co.
B4: Method | C4: Low | D4: Implied | E4: High | F4: Weights
B5: DCF | C5: =DCF!K36 -> 71.863686 | D5: =DCF!I38 -> 105.23211 | E5: =DCF!G40 -> 216.65965 | F5: 0.2
B6: EV/Revenue | C6: ='Comparable Comps Valuation'!O44 -> 34.518652 | D6: ='Comparable Comps Valuation'!O30 -> 108.41554 | E6: ='Comparable Comps Valuation'!O37 -> 293.76977 | F6: 0.2
B7: EV/EBITDA | C7: ='Comparable Comps Valuation'!P44 -> 47.486448 | D7: ='Comparable Comps Valuation'!P30 -> 94.623869 | E7: ='Comparable Comps Valuation'!P37 -> 233.51313 | F7: 0.2
B8: EV/EBIT | C8: ='Comparable Comps Valuation'!Q44 -> 62.87733 | D8: ='Comparable Comps Valuation'!Q30 -> 134.99766 | E8: ='Comparable Comps Valuation'!Q37 -> 515.39773 | F8: 0.2
B9: P/E | C9: ='Comparable Comps Valuation'!R44 -> 36.546749 | D9: ='Comparable Comps Valuation'!R30 -> 91.475405 | E9: ='Comparable Comps Valuation'!R37 -> 134.69122 | F9: 0.2
D10: =SUMPRODUCT(D5:D9,F5:F9) -> 106.94892 | F10: =SUM(F5:F9) -> 1
B13: Method | C13: Opening | D13: High | E13: Low | F13: Close
B14: DCF | C14: =D5 -> 105.23211 | D14: =E5 -> 216.65965 | E14: =C5 -> 71.863686 | F14: =E14 -> 71.863686
B15: EV/Revenue | C15: =D6 -> 108.41554 | D15: =E6 -> 293.76977 | E15: =C6 -> 34.518652 | F15: =E15 -> 34.518652
B16: EV/EBITDA | C16: =D7 -> 94.623869 | D16: =E7 -> 233.51313 | E16: =C7 -> 47.486448 | F16: =E16 -> 47.486448
B17: EV/EBIT | C17: =D8 -> 134.99766 | D17: =E8 -> 515.39773 | E17: =C8 -> 62.87733 | F17: =E17 -> 62.87733
B18: P/E | C18: =D9 -> 91.475405 | D18: =E9 -> 134.69122 | E18: =C9 -> 36.546749 | F18: =E18 -> 36.546749
B21: Premium Analysis
B22: 30% Premium over Implied Value/Share | D22: =D10*(1+30%) -> 139.03359
B23: Shares O/s | D23: ='Comparable Comps'!D25 -> 122
B24: Equity Value after Premium | D24: =D22*D23 -> 16962.098
